AUTHORS.rst
CHANGES
CONTRIBUTING.rst
MANIFEST.in
README.rst
SCRIPTS
TODO
requirements.txt
setup.py
mqt/__about__.py
mqt/__init__.py
mqt/_compat.py
mqt/cli.py
mqt/getaddons.py
mqt/git_run.py
mqt/helpers.py
mqt/lints.py
mqt/mqt.py
mqt.egg-info/PKG-INFO
mqt.egg-info/SOURCES.txt
mqt.egg-info/dependency_links.txt
mqt.egg-info/entry_points.txt
mqt.egg-info/not-zip-safe
mqt.egg-info/requires.txt
mqt.egg-info/top_level.txt
mqt/testsuite/__init__.py
mqt/testsuite/helpers.py
mqt/testsuite/mqt.py