Metadata-Version: 1.1
Name: mqt
Version: 0.1.1
Summary: QA Tools for Odoo maintainers (MQT)
Home-page: https://github.com/oca/mqt
Author: Odoo Community Association
Author-email: github@odoo-community.org
License: AGPL-v3
Keywords: mqt
Platform: UNKNOWN
Classifier: Development Status :: 2 - Pre-Alpha
Classifier: Intended Audience :: Developers
Classifier: License :: OSI Approved :: BSD License
Classifier: Natural Language :: English
Classifier: Programming Language :: Python :: 2
Classifier: Programming Language :: Python :: 2.6
Classifier: Programming Language :: Python :: 2.7
Classifier: Programming Language :: Python :: 3
Classifier: Programming Language :: Python :: 3.3
